build/lib/ka_uts_dic/__init__.py
build/lib/ka_uts_dic/__version__.py
build/lib/ka_uts_dic/dic.py
build/lib/ka_uts_dic/doa.py
build/lib/ka_uts_dic/doaod.py
build/lib/ka_uts_dic/doc.py
build/lib/ka_uts_dic/dod.py
build/lib/ka_uts_dic/dodoa.py
build/lib/ka_uts_dic/dodod.py
build/lib/ka_uts_dic/dodows.py
build/lib/ka_uts_dic/doeq.py
build/lib/ka_uts_dic/doo.py
build/lib/ka_uts_dic/dopddf.py
build/lib/ka_uts_dic/dopldf.py
build/lib/ka_uts_dic/py.typed
ka_uts_dic/__init__.py
ka_uts_dic/__version__.py
ka_uts_dic/dic.py
ka_uts_dic/doa.py
ka_uts_dic/doaod.py
ka_uts_dic/doc.py
ka_uts_dic/dod.py
ka_uts_dic/dodoa.py
ka_uts_dic/dodod.py
ka_uts_dic/dodows.py
ka_uts_dic/doeq.py
ka_uts_dic/doo.py
ka_uts_dic/dopddf.py
ka_uts_dic/dopldf.py
ka_uts_dic/py.typed
ka_uts_dic-4.1.0.250525.dist-info/licenses/LICENSE.txt
ka_uts_dic-4.1.0.250525.dist-info/METADATA
ka_uts_dic-4.1.0.250525.dist-info/WHEEL
ka_uts_dic-4.1.0.250525.dist-info/top_level.txt
ka_uts_dic-4.1.0.250525.dist-info/RECORD
