Metadata-Version: 2.4
Name: ka_uts_dic
Version: 4.1.0.250525
Summary: Dictionary Utilities
Author-email: Bernd Stroehle <bernd.stroehle@gmail.com>
Maintainer-email: Bernd Stroehle <bernd.stroehle@gmail.com>
License-Expression: GPL-3.0-only WITH Classpath-exception-2.0 OR BSD-3-Clause
Project-URL: Source Code, https://github.com/bs29/ka_uts_dic/tree/master
Project-URL: Homepage, https://kosakya.de/
Project-URL: Documentation, https://ka-apc.readthedocs.io/en/latest
Classifier: Development Status :: 5 - Production/Stable
Classifier: Intended Audience :: Developers
Classifier: Operating System :: OS Independent
Classifier: Programming Language :: Python :: 3.12
Classifier: Natural Language :: English
Classifier: Topic :: Software Development :: Libraries :: Python Modules
Requires-Python: >=3.10
License-File: LICENSE.txt
Requires-Dist: ka_uts_aod>=4.1.0.250525
Requires-Dist: ka_uts_dfr>=4.1.0.250525
Requires-Dist: ka_uts_log>=4.1.0.250525
Requires-Dist: ka_uts_obj>=4.1.0.250525
Requires-Dist: numpy>=2.2.6
Requires-Dist: openpyxl>=3.1.5
Requires-Dist: pandas>=2.2.3
Requires-Dist: polars>=1.30.0
Dynamic: license-file
